fis_calculator/__init__.py
fis_calculator/fis_calculator_src.py
fis_calculator-0.0.1.dist-info/METADATA
fis_calculator-0.0.1.dist-info/WHEEL
fis_calculator-0.0.1.dist-info/top_level.txt
fis_calculator-0.0.1.dist-info/RECORD
