Metadata-Version: 2.1
Name: fis-calculator
Version: 0.0.1
Summary: FIS calculator for neurological protein-protein interactions
Author: Neural Dynamics Group
Author-email: <shreyankkadadi@gmail.com>
Keywords: python,neuroscience,protein-protein,biology
Classifier: Development Status :: 1 - Planning
Classifier: Programming Language :: Python :: 3
Classifier: Operating System :: Unix
Classifier: Operating System :: MacOS :: MacOS X
Classifier: Operating System :: Microsoft :: Windows
Requires-Dist: numpy
Requires-Dist: pandas
